spleeter/__init__.py
spleeter/__main__.py
spleeter/audio/__init__.py
spleeter/audio/adapter.py
spleeter/audio/convertor.py
spleeter/audio/ffmpeg.py
spleeter/model/__init__.py
spleeter/model/functions/__init__.py
spleeter/model/functions/blstm.py
spleeter/model/functions/unet.py
spleeter/options.py
spleeter/pretrained_models/2stems/._checkpoint
spleeter/pretrained_models/2stems/.probe
spleeter/pretrained_models/2stems/checkpoint
spleeter/pretrained_models/2stems/model.data-00000-of-00001
spleeter/pretrained_models/2stems/model.index
spleeter/pretrained_models/2stems/model.meta
spleeter/py.typed
spleeter/separator.py
spleeter/types.py
spleeter/utils/__init__.py
spleeter/utils/configuration.py
spleeter/utils/downloader.py
spleeter/utils/logging.py
spleeter/utils/tensor.py
lite_spleeter-2.1.0.dist-info/LICENSE
lite_spleeter-2.1.0.dist-info/METADATA
lite_spleeter-2.1.0.dist-info/WHEEL
lite_spleeter-2.1.0.dist-info/entry_points.txt
lite_spleeter-2.1.0.dist-info/RECORD
